<?xml version="1.0" encoding="utf-8"?>
	<annotation>
		<folder>driving_annotation_dataset</folder>
		<filename>image_3387.jpg</filename>
		<size>
			<width>1280</width>
			<height>720</height>
			<depth>3</depth>
		</size>
		<object>
			<name>insulator_pin</name>
			<pose>Unspecified</pose>
			<truncated>0</truncated>
			<difficult>0</difficult>
			<bndbox>
				<xmin>189</xmin>
				<ymin>392</ymin>
				<xmax>249</xmax>
				<ymax>443</ymax>
			</bndbox>
		</object>
		<object>
			<name>insulator_pin</name>
			<pose>Unspecified</pose>
			<truncated>0</truncated>
			<difficult>0</difficult>
			<bndbox>
				<xmin>629</xmin>
				<ymin>201</ymin>
				<xmax>700</xmax>
				<ymax>254</ymax>
			</bndbox>
		</object>
		<object>
			<name>insulator_pin</name>
			<pose>Unspecified</pose>
			<truncated>0</truncated>
			<difficult>0</difficult>
			<bndbox>
				<xmin>859</xmin>
				<ymin>94</ymin>
				<xmax>932</xmax>
				<ymax>152</ymax>
			</bndbox>
		</object>
		<object>
			<name>insulator_pin</name>
			<pose>Unspecified</pose>
			<truncated>0</truncated>
			<difficult>0</difficult>
			<bndbox>
				<xmin>957</xmin>
				<ymin>150</ymin>
				<xmax>1027</xmax>
				<ymax>207</ymax>
			</bndbox>
		</object>
	</annotation>
